README.rst
setup.py
polytiles/__init__.py
polytiles/polytiles.py
polytiles.egg-info/PKG-INFO
polytiles.egg-info/SOURCES.txt
polytiles.egg-info/dependency_links.txt
polytiles.egg-info/entry_points.txt
polytiles.egg-info/requires.txt
polytiles.egg-info/top_level.txt