Metadata-Version: 1.1
Name: polytiles
Version: 1.0.1
Summary: A script to render tiles for an area with mapnik
Home-page: https://github.com/zverik/polytiles
Author: Ilya Zverev
Author-email: ilya@zverev.info
License: WTFPL
Platform: UNKNOWN
Classifier: Development Status :: 5 - Production/Stable
Classifier: Environment :: Console
Classifier: Intended Audience :: Information Technology
Classifier: Natural Language :: English
Classifier: Operating System :: OS Independent
Classifier: Topic :: Utilities
Classifier: License :: Public Domain
Classifier: Programming Language :: Python :: 2
Classifier: Programming Language :: Python :: 3
